dex/__init__.py
dex/data_model.py
dex/isbn_utils.py
dex/library.py
dex/log_utils.py
dex/multiproc_utils.py
dex/ocr_utils.py
dex/path_utils.py
dex/py.typed
spindex-0.0.7.dist-info/METADATA
spindex-0.0.7.dist-info/WHEEL
spindex-0.0.7.dist-info/top_level.txt
spindex-0.0.7.dist-info/RECORD
